tqsdk_zq_server/__init__.py
tqsdk_zq_server-1.0.6.dist-info/METADATA
tqsdk_zq_server-1.0.6.dist-info/WHEEL
tqsdk_zq_server-1.0.6.dist-info/top_level.txt
tqsdk_zq_server-1.0.6.dist-info/RECORD
