Metadata-Version: 2.1
Name: tqsdk-zq-server
Version: 1.0.6
Summary: TianQin SDK - zq_server lib
Home-page: https://www.shinnytech.com/tqsdk
Author: TianQin
Author-email: tianqincn@gmail.com
License: UNKNOWN
Platform: UNKNOWN
Requires-Python: >=3
